bitkub/__init__.py
python_bitkub-0.0.1.dist-info/LICENSE
python_bitkub-0.0.1.dist-info/METADATA
python_bitkub-0.0.1.dist-info/WHEEL
python_bitkub-0.0.1.dist-info/top_level.txt
python_bitkub-0.0.1.dist-info/RECORD
