Metadata-Version: 2.1
Name: python-bitkub
Version: 0.0.1
Summary: A Python wrapper for Bitkub API
Author-email: Praphan Klairith <p.klairith@gmail.com>
Project-URL: Homepage, https://github.com/xbklairith/python-bitkub
Project-URL: Bug Tracker, https://github.com/xbklairith/python-bitkub/issues
Classifier: Programming Language :: Python :: 3
Classifier: License :: OSI Approved :: MIT License
Classifier: Operating System :: OS Independent
Requires-Python: >=3.7
License-File: LICENSE
